arducam_200mp_convert_lib.cpython-37m-x86_64-linux-gnu.so
arducam_200mp_convert_lib-0.1.0.dist-info/METADATA
arducam_200mp_convert_lib-0.1.0.dist-info/WHEEL
arducam_200mp_convert_lib-0.1.0.dist-info/RECORD
arducam_200mp_convert_lib-0.1.0.dist-info/top_level.txt
